setup.cfg
setup.py
SAMLSchtron.egg-info/PKG-INFO
SAMLSchtron.egg-info/SOURCES.txt
SAMLSchtron.egg-info/dependency_links.txt
SAMLSchtron.egg-info/not-zip-safe
SAMLSchtron.egg-info/requires.txt
SAMLSchtron.egg-info/top_level.txt
rules/__init__.py
saml_schtron/__init__.py
saml_schtron/loggingconfig.py
saml_schtron/validator.py
saml_schtron/xmlschemavalidator.py
saml_schtron/webapp/__init__.py
saml_schtron/webapp/app_handler.py
saml_schtron/webapp/config.py
scripts/start_srv.py
scripts/val_schtron.sh
scripts/val_xsd.sh
scripts/validate.py
test/__init__.py
test/assertNoDiff.py
test/testXsdValidator.py
test/test_validator.py
testdata/__init__.py
xmlschema/__init__.py