Metadata-Version: 1.1
Name: SAMLSchtron
Version: 0.3.3
Summary: SAML Metadata Schematron Validator: CLI, API & Web Server
Home-page: https://github.com/rhoerbe/saml_schematron
Author: Rainer Hörbe
Author-email: rainer@hoerbe.at
License: UNKNOWN
Keywords: identity federation saml metadata
Platform: UNKNOWN
Classifier: Development Status :: 4 - Beta
Classifier: Intended Audience :: Information Technology
Classifier: License :: OSI Approved :: European Union Public Licence 1.1 (EUPL 1.1)
Classifier: Programming Language :: Python :: 3 :: Only
Classifier: Programming Language :: Python :: 3.4
Classifier: Programming Language :: Python :: 3.5
Classifier: Topic :: System :: Systems Administration
